MANIFEST.in
README.rst
setup.cfg
setup.py
docs/Makefile
docs/conf.py
docs/index.rst
docs/make.bat
thirty_cli.egg-info/PKG-INFO
thirty_cli.egg-info/SOURCES.txt
thirty_cli.egg-info/dependency_links.txt
thirty_cli.egg-info/entry_points.txt
thirty_cli.egg-info/requires.txt
thirty_cli.egg-info/top_level.txt
thirtycli/__init__.py
thirtycli/shell.py
thirtycli/utils.py
thirtycli/actions/__init__.py
thirtycli/actions/common.py
thirtycli/actions/create.py
thirtycli/actions/delete.py
thirtycli/actions/deploy.py
thirtycli/actions/djangocmd.py
thirtycli/actions/list.py
thirtycli/actions/logbook.py
thirtycli/actions/logs.py
thirtycli/actions/publish.py
thirtycli/actions/restart.py
thirtycli/actions/restore.py
thirtycli/actions/runcmd.py
thirtycli/actions/scale.py
thirtycli/actions/setup.py
thirtycli/actions/show.py
thirtycli/actions/update.py
thirtycli/actions/usage.py