Metadata-Version: 1.1
Name: thirty-cli
Version: 0.4
Summary: A high level management tool for the 30loops platform.
Home-page: http://30loops.net/
Author: 30loops.net team
Author-email: crito@30loops.net
License: BSD
Platform: UNKNOWN
Classifier: Development Status :: 4 - Beta
Classifier: Environment :: Console
Classifier: Intended Audience :: Developers
Classifier: License :: OSI Approved :: BSD License
Classifier: Operating System :: OS Independent
Classifier: Programming Language :: Python
Classifier: Topic :: Internet :: WWW/HTTP
